ensemble_methods/__init__.py
ensemble_methods/adaBoost.py
ensemble_methods/bagging.py
ensemble_methods/gradient_boosting.py
ensemble_methods/randomForest.py
ensemble_methods/stacking.py
metrics_model_evaluation/__init__.py
metrics_model_evaluation/accuracy.py
metrics_model_evaluation/confusion_matrix.py
metrics_model_evaluation/f1_score.py
metrics_model_evaluation/mean_absolute_error.py
metrics_model_evaluation/mean_squared_error.py
metrics_model_evaluation/precision.py
metrics_model_evaluation/r2_score.py
metrics_model_evaluation/recall.py
model_selection/__init__.py
model_selection/cross_validation.py
model_selection/grid_search.py
model_selection/kfold.py
model_selection/make_scorer.py
model_selection/param_grid.py
model_selection/train_test_split.py
preprocessing/__init__.py
preprocessing/impute_missing_values_mean.py
preprocessing/impute_missing_values_median.py
preprocessing/impute_missing_values_mode.py
preprocessing/labelencoder.py
preprocessing/normalize_features.py
preprocessing/numerical_categorical_variables.py
preprocessing/onehotencoder.py
preprocessing/outliers.py
preprocessing/scale_features_min_max.py
preprocessing/scale_features_standard.py
preprocessing/select_features.py
supervised_learning/DecisionTree.py
supervised_learning/LinearRegression.py
supervised_learning/LogisticRegression.py
supervised_learning/NaiveBayes.py
supervised_learning/NeuralNetwork.py
supervised_learning/__init__.py
supervised_learning/knn.py
testing/__init__.py
testing/adaboost.py
testing/bagging.py
testing/cross_validation.py
testing/cross_validation_iris.py
testing/data_loading.py
testing/gradient_boosting.py
testing/grid_search.py
testing/grid_search_cv.py
testing/helpers.py
testing/impute_missing_values_mean.py
testing/impute_missing_values_median.py
testing/impute_missing_values_mode.py
testing/kfold_test.py
testing/labelencoder.py
testing/make_scorer.py
testing/metrics_test.py
testing/models_test.py
testing/neural_network_test.py
testing/normalize_features.py
sktlearn_clone-0.2.0.dist-info/METADATA
sktlearn_clone-0.2.0.dist-info/WHEEL
sktlearn_clone-0.2.0.dist-info/top_level.txt
sktlearn_clone-0.2.0.dist-info/RECORD
